{
  "schemaVersion": "1.1.0",
  "lastUpdated": "2026-04-21T20:49:15Z",
  "sources": [
    "vinow"
  ],
  "counts": {
    "totalDays": 15,
    "totalShipCalls": 25,
    "totalPassengers": 103532,
    "shipsWithUnknownDock": [
      "Allure of the Seas",
      "Celebrity Beyond",
      "Icon of the Seas",
      "Radiance of the Seas",
      "Star of the Seas",
      "Wonder of the Seas"
    ]
  },
  "days": [
    {
      "date": "2026-05-03",
      "ships": [
        {
          "name": "Radiance of the Seas",
          "line": "",
          "passengers": 2142,
          "dock": "Unknown",
          "rawDock": "CB",
          "arrival": "08:00",
          "departure": "18:00"
        }
      ]
    },
    {
      "date": "2026-05-05",
      "ships": [
        {
          "name": "Carnival Vista",
          "line": "",
          "passengers": 3936,
          "dock": "WICO",
          "rawDock": "WICO",
          "arrival": "09:00",
          "departure": "18:00"
        },
        {
          "name": "Wonder of the Seas",
          "line": "",
          "passengers": 6988,
          "dock": "Unknown",
          "rawDock": "CB",
          "arrival": "08:00",
          "departure": "18:00"
        },
        {
          "name": "Norwegian Luna",
          "line": "",
          "passengers": 3550,
          "dock": "WICO",
          "rawDock": "WICO",
          "arrival": "11:00",
          "departure": "19:00"
        }
      ]
    },
    {
      "date": "2026-05-06",
      "ships": [
        {
          "name": "Norwegian Prima",
          "line": "",
          "passengers": 3215,
          "dock": "WICO",
          "rawDock": "WICO",
          "arrival": "13:30",
          "departure": "20:00"
        },
        {
          "name": "Star of the Seas",
          "line": "",
          "passengers": 5600,
          "dock": "Unknown",
          "rawDock": "CB",
          "arrival": "07:00",
          "departure": "20:00"
        }
      ]
    },
    {
      "date": "2026-05-07",
      "ships": [
        {
          "name": "Allure of the Seas",
          "line": "",
          "passengers": 5408,
          "dock": "Unknown",
          "rawDock": "CB",
          "arrival": "07:00",
          "departure": "15:30"
        },
        {
          "name": "Carnival Venezia",
          "line": "",
          "passengers": 4090,
          "dock": "WICO",
          "rawDock": "WICO",
          "arrival": "07:00",
          "departure": "16:00"
        }
      ]
    },
    {
      "date": "2026-05-12",
      "ships": [
        {
          "name": "Norwegian Luna",
          "line": "",
          "passengers": 3550,
          "dock": "WICO",
          "rawDock": "WICO",
          "arrival": "11:00",
          "departure": "19:00"
        }
      ]
    },
    {
      "date": "2026-05-13",
      "ships": [
        {
          "name": "Carnival Celebration",
          "line": "",
          "passengers": 5282,
          "dock": "WICO",
          "rawDock": "WICO",
          "arrival": "07:00",
          "departure": "16:00"
        },
        {
          "name": "Disney Treasure",
          "line": "",
          "passengers": 4000,
          "dock": "WICO",
          "rawDock": "WICO",
          "arrival": "06:30",
          "departure": "16:00"
        }
      ]
    },
    {
      "date": "2026-05-14",
      "ships": [
        {
          "name": "Carnival Venezia",
          "line": "",
          "passengers": 4090,
          "dock": "WICO",
          "rawDock": "WICO",
          "arrival": "07:00",
          "departure": "16:00"
        }
      ]
    },
    {
      "date": "2026-05-17",
      "ships": [
        {
          "name": "Radiance of the Seas",
          "line": "",
          "passengers": 2142,
          "dock": "Unknown",
          "rawDock": "CB",
          "arrival": "08:00",
          "departure": "18:00"
        }
      ]
    },
    {
      "date": "2026-05-19",
      "ships": [
        {
          "name": "Norwegian Luna",
          "line": "",
          "passengers": 3550,
          "dock": "WICO",
          "rawDock": "WICO",
          "arrival": "11:00",
          "departure": "19:00"
        }
      ]
    },
    {
      "date": "2026-05-20",
      "ships": [
        {
          "name": "Norwegian Prima",
          "line": "",
          "passengers": 3215,
          "dock": "WICO",
          "rawDock": "WICO",
          "arrival": "13:30",
          "departure": "20:00"
        },
        {
          "name": "Icon of the Seas",
          "line": "",
          "passengers": 7600,
          "dock": "Unknown",
          "rawDock": "CB",
          "arrival": "07:00",
          "departure": "14:30"
        }
      ]
    },
    {
      "date": "2026-05-21",
      "ships": [
        {
          "name": "Carnival Magic",
          "line": "",
          "passengers": 3690,
          "dock": "WICO",
          "rawDock": "WICO",
          "arrival": "07:00",
          "departure": "16:00"
        }
      ]
    },
    {
      "date": "2026-05-24",
      "ships": [
        {
          "name": "Carnival Venezia",
          "line": "",
          "passengers": 4090,
          "dock": "WICO",
          "rawDock": "WICO",
          "arrival": "08:00",
          "departure": "17:00"
        }
      ]
    },
    {
      "date": "2026-05-26",
      "ships": [
        {
          "name": "Disney Treasure",
          "line": "",
          "passengers": 4000,
          "dock": "WICO",
          "rawDock": "WICO",
          "arrival": "06:45",
          "departure": "17:00"
        },
        {
          "name": "Norwegian Luna",
          "line": "",
          "passengers": 3550,
          "dock": "WICO",
          "rawDock": "WICO",
          "arrival": "11:00",
          "departure": "19:00"
        }
      ]
    },
    {
      "date": "2026-05-27",
      "ships": [
        {
          "name": "Regal Princess",
          "line": "",
          "passengers": 3560,
          "dock": "WICO",
          "rawDock": "WICO",
          "arrival": "07:00",
          "departure": "16:00"
        },
        {
          "name": "Carnival Celebration",
          "line": "",
          "passengers": 5282,
          "dock": "WICO",
          "rawDock": "WICO",
          "arrival": "09:00",
          "departure": "18:00"
        },
        {
          "name": "Celebrity Beyond",
          "line": "",
          "passengers": 3260,
          "dock": "Unknown",
          "rawDock": "CB",
          "arrival": "10:00",
          "departure": "18:00"
        },
        {
          "name": "Star of the Seas",
          "line": "",
          "passengers": 5600,
          "dock": "Unknown",
          "rawDock": "CB",
          "arrival": "12:30",
          "departure": "20:00"
        }
      ]
    },
    {
      "date": "2026-05-31",
      "ships": [
        {
          "name": "Radiance of the Seas",
          "line": "",
          "passengers": 2142,
          "dock": "Unknown",
          "rawDock": "CB",
          "arrival": "08:00",
          "departure": "18:00"
        }
      ]
    }
  ]
}
